{
    "dev": {
        "environment": "development",
        "platform": "web",
        "defaultRoute": "defaultAppRoute",
        "defaultAuthenticatedRoute": "defaultAuthRoute",
        "defaultLayout": "WrappidAppLayout",
        "defaultAuthenticatedLayout": "AppContainerLayout",
        "backendUrl": "",
        "webUrl": "http://localhost:3000",
        "drawerWidth": 240,
        "miniDrawerWidth": 56,
        "snackMessage": false,
        "otpLength": 6,
        "socialLogin": {
            "enable": true,
            "github": {
                "enable": true,
                "apiKey": "xxxxxxxxxxxxxxxxxxxxxxxx",
                "apiKeySecret": "xxxxxxxxxxxxxxxxxxxxxxxx",
                "callbackURL": "xxxxxxxxxxxxxxxxxxxxxxxx"
            },
            "facebook": {
                "enable": true,
                "apiKey": "xxxxxxxxxxxxxxxxxxxxxxxx",
                "apiKeySecret": "xxxxxxxxxxxxxxxxxxxxxxxx",
                "callbackURL": "xxxxxxxxxxxxxxxxxxxxxxxx"
            },
            "linkedin": {
                "enable": true,
                "apiKey": "xxxxxxxxxxxxxxxxxxxxxxxx",
                "apiKeySecret": "xxxxxxxxxxxxxxxxxxxxxxxx",
                "callbackURL": "xxxxxxxxxxxxxxxxxxxxxxxx"
            }
        }
    },
    "stage": {
        "environment": "stage",
        "platform": "web",
        "defaultRoute": "defaultAppRoute",
        "defaultAuthenticatedRoute": "defaultAuthRoute",
        "defaultLayout": "WrappidAppLayout",
        "defaultAuthenticatedLayout": "AppContainerLayout",
        "backendUrl": "https://demoapi.wrappid.dev",
        "webUrl": "http://localhost:3000",
        "drawerWidth": 240,
        "miniDrawerWidth": 56,
        "snackMessage": false,
        "otpLength": 6,
        "socialLogin": {
            "enable": true,
            "github": {
                "enable": true,
                "apiKey": "xxxxxxxxxxxxxxxxxxxxxxxx",
                "apiKeySecret": "xxxxxxxxxxxxxxxxxxxxxxxx",
                "callbackURL": "xxxxxxxxxxxxxxxxxxxxxxxx"
            },
            "facebook": {
                "enable": true,
                "apiKey": "xxxxxxxxxxxxxxxxxxxxxxxx",
                "apiKeySecret": "xxxxxxxxxxxxxxxxxxxxxxxx",
                "callbackURL": "xxxxxxxxxxxxxxxxxxxxxxxx"
            },
            "linkedin": {
                "enable": true,
                "apiKey": "xxxxxxxxxxxxxxxxxxxxxxxx",
                "apiKeySecret": "xxxxxxxxxxxxxxxxxxxxxxxx",
                "callbackURL": "xxxxxxxxxxxxxxxxxxxxxxxx"
            }
        }
    },
    "prod": {
        "environment": "production",
        "platform": "web",
        "defaultRoute": "defaultAppRoute",
        "defaultAuthenticatedRoute": "defaultAuthRoute",
        "defaultLayout": "WrappidAppLayout",
        "defaultAuthenticatedLayout": "AppContainerLayout",
        "backendUrl": "",
        "webUrl": "http://localhost:3000",
        "drawerWidth": 240,
        "miniDrawerWidth": 56,
        "snackMessage": false,
        "otpLength": 6,
        "socialLogin": {
            "enable": true,
            "github": {
                "enable": true,
                "apiKey": "xxxxxxxxxxxxxxxxxxxxxxxx",
                "apiKeySecret": "xxxxxxxxxxxxxxxxxxxxxxxx",
                "callbackURL": "xxxxxxxxxxxxxxxxxxxxxxxx"
            },
            "facebook": {
                "enable": true,
                "apiKey": "xxxxxxxxxxxxxxxxxxxxxxxx",
                "apiKeySecret": "xxxxxxxxxxxxxxxxxxxxxxxx",
                "callbackURL": "xxxxxxxxxxxxxxxxxxxxxxxx"
            },
            "linkedin": {
                "enable": true,
                "apiKey": "xxxxxxxxxxxxxxxxxxxxxxxx",
                "apiKeySecret": "xxxxxxxxxxxxxxxxxxxxxxxx",
                "callbackURL": "xxxxxxxxxxxxxxxxxxxxxxxx"
            }
        }
    }
}